GenGraph/__init__.py
GenGraph/gengraph.py
GenGraph/gengraphTool.py
GenGraph/gengraph_newfunctions.py
GenGraph/unitTest_GG.py
GenGraph-0.2.dist-info/METADATA
GenGraph-0.2.dist-info/WHEEL
GenGraph-0.2.dist-info/top_level.txt
GenGraph-0.2.dist-info/RECORD
