Metadata-Version: 2.1
Name: GenGraph
Version: 0.2
Summary: Tools for the creation and use of genome graphs
Home-page: https://github.com/jambler24/GenGraph
Author: Jon Ambler
Author-email: jambler24@gmail.com
License: UNKNOWN
Platform: UNKNOWN
Classifier: Programming Language :: Python :: 3
Classifier: License :: OSI Approved :: GNU General Public License v3 (GPLv3)
Classifier: Operating System :: OS Independent
Requires-Dist: networkx
Requires-Dist: numpy
Requires-Dist: matplotlib
Requires-Dist: pandas
Requires-Dist: biopython
